stactools/sentinel5p/__init__.py
stactools/sentinel5p/commands.py
stactools/sentinel5p/constants.py
stactools/sentinel5p/metadata_links.py
stactools/sentinel5p/product_metadata.py
stactools/sentinel5p/properties.py
stactools/sentinel5p/stac.py
stactools_sentinel5p-0.2.0.dist-info/LICENSE
stactools_sentinel5p-0.2.0.dist-info/METADATA
stactools_sentinel5p-0.2.0.dist-info/WHEEL
stactools_sentinel5p-0.2.0.dist-info/top_level.txt
stactools_sentinel5p-0.2.0.dist-info/RECORD
