Metadata-Version: 2.1
Name: stactools-sentinel5p
Version: 0.2.0
Summary: Stactools package for Sentinel-5P level 2 Products
Home-page: https://github.com/stactools-packages/sentinel5p
Author: Chung-Xiang Hong
Author-email: chung.horng@sinergise.com
License: UNKNOWN
Project-URL: Issues, https://github.com/stactools-packages/sentinel5p/issues
Keywords: stactools,pystac,catalog,STAC,sentinel,level 2,AER_AI,AER_LH,CH4___,CLOUD_,CO____,HCHO__,NO2___,O3____,O3_TCL,SO2___,NP_BD3,NP_BD6,NP_BD7
Platform: UNKNOWN
Classifier: Development Status :: 4 - Beta
Classifier: License :: OSI Approved :: Apache Software License
Classifier: Programming Language :: Python :: 3.7
Classifier: Programming Language :: Python :: 3.8
Classifier: Programming Language :: Python :: 3.9
License-File: LICENSE
Requires-Dist: stactools (==0.2.1)
